p2p/__init__.py
p2p/_utils.py
p2p/abc.py
p2p/asyncio_utils.py
p2p/auth.py
p2p/behaviors.py
p2p/commands.py
p2p/connection.py
p2p/constants.py
p2p/disconnect.py
p2p/discovery.py
p2p/ecies.py
p2p/events.py
p2p/exceptions.py
p2p/handshake.py
p2p/kademlia.py
p2p/logging.py
p2p/logic.py
p2p/message.py
p2p/metrics.py
p2p/multiplexer.py
p2p/p2p_api.py
p2p/p2p_proto.py
p2p/peer.py
p2p/peer_backend.py
p2p/peer_pool.py
p2p/protocol.py
p2p/qualifiers.py
p2p/receipt.py
p2p/resource_lock.py
p2p/session.py
p2p/subscription.py
p2p/token_bucket.py
p2p/transport.py
p2p/trio_utils.py
p2p/typing.py
p2p/validation.py
p2p/exchange/__init__.py
p2p/exchange/abc.py
p2p/exchange/candidate_stream.py
p2p/exchange/constants.py
p2p/exchange/exchange.py
p2p/exchange/logic.py
p2p/exchange/manager.py
p2p/exchange/normalizers.py
p2p/exchange/tracker.py
p2p/exchange/typing.py
p2p/exchange/validator.py
p2p/stats/__init__.py
p2p/stats/ema.py
p2p/stats/percentile.py
p2p/stats/stddev.py
p2p/tools/__init__.py
p2p/tools/asyncio_streams.py
p2p/tools/connection.py
p2p/tools/handshake.py
p2p/tools/memory_transport.py
p2p/tools/factories/__init__.py
p2p/tools/factories/connection.py
p2p/tools/factories/kademlia.py
p2p/tools/factories/keys.py
p2p/tools/factories/multiplexer.py
p2p/tools/factories/p2p_proto.py
p2p/tools/factories/peer.py
p2p/tools/factories/protocol.py
p2p/tools/factories/session.py
p2p/tools/factories/socket.py
p2p/tools/factories/transport.py
p2p/tools/paragon/__init__.py
p2p/tools/paragon/api.py
p2p/tools/paragon/commands.py
p2p/tools/paragon/payloads.py
p2p/tools/paragon/peer.py
p2p/tools/paragon/proto.py
p2p/tracking/__init__.py
p2p/tracking/connection.py
scripts/__init__.py
scripts/chainsync.py
scripts/discovery.py
scripts/mine_devnet.py
scripts/peer.py
scripts/upnp.py
trinity/__init__.py
trinity/boot_info.py
trinity/bootstrap.py
trinity/cli_parser.py
trinity/config.py
trinity/constants.py
trinity/contextgroup.py
trinity/events.py
trinity/exceptions.py
trinity/initialization.py
trinity-0.1.0a37.dist-info/LICENSE
trinity-0.1.0a37.dist-info/METADATA
trinity-0.1.0a37.dist-info/WHEEL
trinity-0.1.0a37.dist-info/entry_points.txt
trinity-0.1.0a37.dist-info/top_level.txt
trinity-0.1.0a37.dist-info/RECORD
