Metadata-Version: 2.1
Name: trinity
Version: 0.1.0a37
Summary: The Trinity client for the Ethereum network
Home-page: https://github.com/ethereum/trinity
Author: Ethereum Foundation
Author-email: piper@pipermerriam.com
License: MIT
Keywords: ethereum blockchain evm trinity
Platform: UNKNOWN
Classifier: Development Status :: 3 - Alpha
Classifier: Intended Audience :: Developers
Classifier: License :: OSI Approved :: MIT License
Classifier: Natural Language :: English
Classifier: Programming Language :: Python :: 3.7
Classifier: Programming Language :: Python :: 3.8
Requires-Python: >=3.7,<4
Requires-Dist: aiohttp (==3.6.0)
Requires-Dist: asks (<3,>=2.4.8)
Requires-Dist: argcomplete (<2,>=1.12.2)
Requires-Dist: asyncio-run-in-process (==0.1.0a10)
Requires-Dist: bloom-filter (==1.3)
Requires-Dist: cachetools (<4.0.0,>=3.1.0)
Requires-Dist: eth-utils (<2,>=1.9.3)
Requires-Dist: ipython (<7.10.0,>=7.8.0)
Requires-Dist: jsonschema (<4,>=3.2)
Requires-Dist: lahja (<0.18,>=0.17.0)
Requires-Dist: mypy-extensions (<0.5.0,>=0.4.3)
Requires-Dist: plyvel (==1.2.0)
Requires-Dist: prometheus-client (==0.7.1)
Requires-Dist: psutil (<6,>=5.7.0)
Requires-Dist: py-evm (==0.4.0a3)
Requires-Dist: pyformance (==0.4)
Requires-Dist: requests (<3,>=2.21)
Requires-Dist: termcolor (<2.0.0,>=1.1.0)
Requires-Dist: upnp-port-forward (<0.2,>=0.1.1)
Requires-Dist: web3 (<6,>=5.12.1)
Requires-Dist: websockets (>=8.1.0)
Requires-Dist: async-service (==0.1.0a11)
Requires-Dist: asyncio-cancel-token (<0.3,>=0.2)
Requires-Dist: async-lru (<1.0.0,>=0.1.0)
Requires-Dist: cached-property (<2,>=1.5.1)
Requires-Dist: coincurve (<16.0.0,>=15.0.0)
Requires-Dist: cryptography (<3.2,>=3.0)
Requires-Dist: eth-enr (<0.4,>=0.3.0)
Requires-Dist: eth-hash (<1,>=0.1.4)
Requires-Dist: eth-keys (<0.4.0,>=0.3.3)
Requires-Dist: eth-typing (<3,>=2.2.2)
Requires-Dist: lru-dict (<2,>=1.1.6)
Requires-Dist: pysha3 (<2.0.0,>=1.0.0)
Requires-Dist: python-snappy (>=0.5.3)
Requires-Dist: rlp[rust-backend] (<3,>=2)
Requires-Dist: SQLAlchemy (<2,>=1.3.3)
Requires-Dist: trio (<0.17,>=0.16.0)
Requires-Dist: trio-typing (<0.6,>=0.5.0)
Requires-Dist: upnpclient (<1,>=0.0.8)
Requires-Dist: uvloop (==0.14.0) ; platform_system == "Linux" or platform_system == "Darwin" or platform_system == "FreeBSD"
Provides-Extra: dev
Requires-Dist: bumpversion (<1,>=0.5.3) ; extra == 'dev'
Requires-Dist: wheel ; extra == 'dev'
Requires-Dist: setuptools (>=36.2.0) ; extra == 'dev'
Requires-Dist: tox (==2.7.0) ; extra == 'dev'
Requires-Dist: twine ; extra == 'dev'
Requires-Dist: async-service (==0.1.0a11) ; extra == 'dev'
Requires-Dist: asyncio-cancel-token (<0.3,>=0.2) ; extra == 'dev'
Requires-Dist: async-lru (<1.0.0,>=0.1.0) ; extra == 'dev'
Requires-Dist: cached-property (<2,>=1.5.1) ; extra == 'dev'
Requires-Dist: coincurve (<16.0.0,>=15.0.0) ; extra == 'dev'
Requires-Dist: cryptography (<3.2,>=3.0) ; extra == 'dev'
Requires-Dist: eth-enr (<0.4,>=0.3.0) ; extra == 'dev'
Requires-Dist: eth-hash (<1,>=0.1.4) ; extra == 'dev'
Requires-Dist: eth-keys (<0.4.0,>=0.3.3) ; extra == 'dev'
Requires-Dist: eth-typing (<3,>=2.2.2) ; extra == 'dev'
Requires-Dist: lru-dict (<2,>=1.1.6) ; extra == 'dev'
Requires-Dist: pysha3 (<2.0.0,>=1.0.0) ; extra == 'dev'
Requires-Dist: python-snappy (>=0.5.3) ; extra == 'dev'
Requires-Dist: rlp[rust-backend] (<3,>=2) ; extra == 'dev'
Requires-Dist: SQLAlchemy (<2,>=1.3.3) ; extra == 'dev'
Requires-Dist: trio (<0.17,>=0.16.0) ; extra == 'dev'
Requires-Dist: trio-typing (<0.6,>=0.5.0) ; extra == 'dev'
Requires-Dist: upnpclient (<1,>=0.0.8) ; extra == 'dev'
Requires-Dist: aiohttp (==3.6.0) ; extra == 'dev'
Requires-Dist: asks (<3,>=2.4.8) ; extra == 'dev'
Requires-Dist: argcomplete (<2,>=1.12.2) ; extra == 'dev'
Requires-Dist: asyncio-run-in-process (==0.1.0a10) ; extra == 'dev'
Requires-Dist: bloom-filter (==1.3) ; extra == 'dev'
Requires-Dist: cachetools (<4.0.0,>=3.1.0) ; extra == 'dev'
Requires-Dist: eth-utils (<2,>=1.9.3) ; extra == 'dev'
Requires-Dist: ipython (<7.10.0,>=7.8.0) ; extra == 'dev'
Requires-Dist: jsonschema (<4,>=3.2) ; extra == 'dev'
Requires-Dist: lahja (<0.18,>=0.17.0) ; extra == 'dev'
Requires-Dist: mypy-extensions (<0.5.0,>=0.4.3) ; extra == 'dev'
Requires-Dist: plyvel (==1.2.0) ; extra == 'dev'
Requires-Dist: prometheus-client (==0.7.1) ; extra == 'dev'
Requires-Dist: psutil (<6,>=5.7.0) ; extra == 'dev'
Requires-Dist: py-evm (==0.4.0a3) ; extra == 'dev'
Requires-Dist: pyformance (==0.4) ; extra == 'dev'
Requires-Dist: requests (<3,>=2.21) ; extra == 'dev'
Requires-Dist: termcolor (<2.0.0,>=1.1.0) ; extra == 'dev'
Requires-Dist: upnp-port-forward (<0.2,>=0.1.1) ; extra == 'dev'
Requires-Dist: web3 (<6,>=5.12.1) ; extra == 'dev'
Requires-Dist: websockets (>=8.1.0) ; extra == 'dev'
Requires-Dist: async-timeout (<4,>=3.0.1) ; extra == 'dev'
Requires-Dist: hypothesis (<5,>=4.45.1) ; extra == 'dev'
Requires-Dist: pexpect (<5,>=4.6) ; extra == 'dev'
Requires-Dist: factory-boy (==2.12.0) ; extra == 'dev'
Requires-Dist: pytest (<5.4,>=5.3.0) ; extra == 'dev'
Requires-Dist: pytest-cov (<3,>=2.11.1) ; extra == 'dev'
Requires-Dist: pytest-mock (<1.13,>=1.12.1) ; extra == 'dev'
Requires-Dist: pytest-randomly (<4,>=3.3.0) ; extra == 'dev'
Requires-Dist: pytest-timeout (<2,>=1.4.2) ; extra == 'dev'
Requires-Dist: pytest-watch (<4.3,>=4.2.0) ; extra == 'dev'
Requires-Dist: pytest-xdist (<2,>=1.34.0) ; extra == 'dev'
Requires-Dist: eth-tester (==0.5.0b3) ; extra == 'dev'
Requires-Dist: pytest (~=5.3) ; extra == 'dev'
Requires-Dist: Sphinx (<1.8.0,>=1.5.5) ; extra == 'dev'
Requires-Dist: sphinx-rtd-theme (>=0.1.9) ; extra == 'dev'
Requires-Dist: sphinxcontrib-asyncio (<0.3,>=0.2.0) ; extra == 'dev'
Requires-Dist: towncrier (<20,>=19.2.0) ; extra == 'dev'
Requires-Dist: flake8 (==3.7.9) ; extra == 'dev'
Requires-Dist: flake8-bugbear (==19.8.0) ; extra == 'dev'
Requires-Dist: mypy (==0.782) ; extra == 'dev'
Requires-Dist: sqlalchemy-stubs (==0.3) ; extra == 'dev'
Requires-Dist: uvloop (==0.14.0) ; (platform_system == "Linux" or platform_system == "Darwin" or platform_system == "FreeBSD") and extra == 'dev'
Provides-Extra: doc
Requires-Dist: pytest (~=5.3) ; extra == 'doc'
Requires-Dist: Sphinx (<1.8.0,>=1.5.5) ; extra == 'doc'
Requires-Dist: sphinx-rtd-theme (>=0.1.9) ; extra == 'doc'
Requires-Dist: sphinxcontrib-asyncio (<0.3,>=0.2.0) ; extra == 'doc'
Requires-Dist: towncrier (<20,>=19.2.0) ; extra == 'doc'
Provides-Extra: lint
Requires-Dist: flake8 (==3.7.9) ; extra == 'lint'
Requires-Dist: flake8-bugbear (==19.8.0) ; extra == 'lint'
Requires-Dist: mypy (==0.782) ; extra == 'lint'
Requires-Dist: sqlalchemy-stubs (==0.3) ; extra == 'lint'
Provides-Extra: p2p
Requires-Dist: async-service (==0.1.0a11) ; extra == 'p2p'
Requires-Dist: asyncio-cancel-token (<0.3,>=0.2) ; extra == 'p2p'
Requires-Dist: async-lru (<1.0.0,>=0.1.0) ; extra == 'p2p'
Requires-Dist: cached-property (<2,>=1.5.1) ; extra == 'p2p'
Requires-Dist: coincurve (<16.0.0,>=15.0.0) ; extra == 'p2p'
Requires-Dist: cryptography (<3.2,>=3.0) ; extra == 'p2p'
Requires-Dist: eth-enr (<0.4,>=0.3.0) ; extra == 'p2p'
Requires-Dist: eth-hash (<1,>=0.1.4) ; extra == 'p2p'
Requires-Dist: eth-keys (<0.4.0,>=0.3.3) ; extra == 'p2p'
Requires-Dist: eth-typing (<3,>=2.2.2) ; extra == 'p2p'
Requires-Dist: lru-dict (<2,>=1.1.6) ; extra == 'p2p'
Requires-Dist: pysha3 (<2.0.0,>=1.0.0) ; extra == 'p2p'
Requires-Dist: python-snappy (>=0.5.3) ; extra == 'p2p'
Requires-Dist: rlp[rust-backend] (<3,>=2) ; extra == 'p2p'
Requires-Dist: SQLAlchemy (<2,>=1.3.3) ; extra == 'p2p'
Requires-Dist: trio (<0.17,>=0.16.0) ; extra == 'p2p'
Requires-Dist: trio-typing (<0.6,>=0.5.0) ; extra == 'p2p'
Requires-Dist: upnpclient (<1,>=0.0.8) ; extra == 'p2p'
Provides-Extra: test
Requires-Dist: async-timeout (<4,>=3.0.1) ; extra == 'test'
Requires-Dist: hypothesis (<5,>=4.45.1) ; extra == 'test'
Requires-Dist: pexpect (<5,>=4.6) ; extra == 'test'
Requires-Dist: factory-boy (==2.12.0) ; extra == 'test'
Requires-Dist: pytest (<5.4,>=5.3.0) ; extra == 'test'
Requires-Dist: pytest-cov (<3,>=2.11.1) ; extra == 'test'
Requires-Dist: pytest-mock (<1.13,>=1.12.1) ; extra == 'test'
Requires-Dist: pytest-randomly (<4,>=3.3.0) ; extra == 'test'
Requires-Dist: pytest-timeout (<2,>=1.4.2) ; extra == 'test'
Requires-Dist: pytest-watch (<4.3,>=4.2.0) ; extra == 'test'
Requires-Dist: pytest-xdist (<2,>=1.34.0) ; extra == 'test'
Requires-Dist: eth-tester (==0.5.0b3) ; extra == 'test'
Provides-Extra: test-asyncio
Requires-Dist: pytest-asyncio (<0.11,>=0.10.0) ; extra == 'test-asyncio'
Requires-Dist: pytest-aiohttp (<0.4,>=0.3.0) ; extra == 'test-asyncio'
Provides-Extra: test-trio
Requires-Dist: pytest-trio (==0.6.0) ; extra == 'test-trio'
Provides-Extra: trinity
Requires-Dist: aiohttp (==3.6.0) ; extra == 'trinity'
Requires-Dist: asks (<3,>=2.4.8) ; extra == 'trinity'
Requires-Dist: argcomplete (<2,>=1.12.2) ; extra == 'trinity'
Requires-Dist: asyncio-run-in-process (==0.1.0a10) ; extra == 'trinity'
Requires-Dist: bloom-filter (==1.3) ; extra == 'trinity'
Requires-Dist: cachetools (<4.0.0,>=3.1.0) ; extra == 'trinity'
Requires-Dist: eth-utils (<2,>=1.9.3) ; extra == 'trinity'
Requires-Dist: ipython (<7.10.0,>=7.8.0) ; extra == 'trinity'
Requires-Dist: jsonschema (<4,>=3.2) ; extra == 'trinity'
Requires-Dist: lahja (<0.18,>=0.17.0) ; extra == 'trinity'
Requires-Dist: mypy-extensions (<0.5.0,>=0.4.3) ; extra == 'trinity'
Requires-Dist: plyvel (==1.2.0) ; extra == 'trinity'
Requires-Dist: prometheus-client (==0.7.1) ; extra == 'trinity'
Requires-Dist: psutil (<6,>=5.7.0) ; extra == 'trinity'
Requires-Dist: py-evm (==0.4.0a3) ; extra == 'trinity'
Requires-Dist: pyformance (==0.4) ; extra == 'trinity'
Requires-Dist: requests (<3,>=2.21) ; extra == 'trinity'
Requires-Dist: termcolor (<2.0.0,>=1.1.0) ; extra == 'trinity'
Requires-Dist: upnp-port-forward (<0.2,>=0.1.1) ; extra == 'trinity'
Requires-Dist: web3 (<6,>=5.12.1) ; extra == 'trinity'
Requires-Dist: websockets (>=8.1.0) ; extra == 'trinity'
Requires-Dist: uvloop (==0.14.0) ; (platform_system == "Linux" or platform_system == "Darwin" or platform_system == "FreeBSD") and extra == 'trinity'
